webnetwork/__init__.py
webnetwork/detector.py
webnetwork/firewall.py
webnetwork-1.2.3.dist-info/METADATA
webnetwork-1.2.3.dist-info/WHEEL
webnetwork-1.2.3.dist-info/entry_points.txt
webnetwork-1.2.3.dist-info/top_level.txt
webnetwork-1.2.3.dist-info/RECORD
