Metadata-Version: 2.4
Name: webnetwork
Version: 1.2.3
Summary: Automatic web server monitoring and defensive DoS/DDoS detection with blocking
Home-page: https://github.com/bytebreach/webnetwork
Author: hackinglab
Author-email: mrfidal@proton.me
License: MIT
Classifier: Development Status :: 5 - Production/Stable
Classifier: Intended Audience :: System Administrators
Classifier: License :: OSI Approved :: MIT License
Classifier: Programming Language :: Python :: 3.8
Classifier: Programming Language :: Python :: 3.9
Classifier: Programming Language :: Python :: 3.10
Classifier: Operating System :: OS Independent
Classifier: Topic :: Security
Classifier: Topic :: System :: Monitoring
Classifier: Topic :: Internet :: WWW/HTTP
Classifier: Topic :: Software Development :: Libraries
Requires-Python: >=3.8
Requires-Dist: requests>=2.28.0
Requires-Dist: scapy>=2.5.0
Dynamic: author
Dynamic: author-email
Dynamic: classifier
Dynamic: description
Dynamic: description-content-type
Dynamic: home-page
Dynamic: license
Dynamic: requires-dist
Dynamic: requires-python
Dynamic: summary
